AUTHORS
CHANGELOG
ChangeLog
LICENSE
MANIFEST.in
README.md
ochlero.service
ochlero.spec
requirements.txt
setup.cfg
setup.py
test-requirements.txt
tox.ini
etc/ochlero.yaml
ochlero/__init__.py
ochlero/ochlero.py
ochlero.egg-info/PKG-INFO
ochlero.egg-info/SOURCES.txt
ochlero.egg-info/dependency_links.txt
ochlero.egg-info/entry_points.txt
ochlero.egg-info/not-zip-safe
ochlero.egg-info/pbr.json
ochlero.egg-info/requires.txt
ochlero.egg-info/top_level.txt
ochlero/tests/__init__.py
ochlero/tests/test_unit.py