Metadata-Version: 1.1
Name: ochlero
Version: 0.2.0
Summary: systemd log monitor that publishes to an MQTT bus on specific events
Home-page: http://softwarefactory-project.io
Author: Matthieu Huin
Author-email: softwarefactory-dev@redhat.com
License: UNKNOWN
Platform: UNKNOWN
Classifier: Intended Audience :: Information Technology
Classifier: Intended Audience :: System Administrators
Classifier: License :: OSI Approved :: Apache Software License
Classifier: Operating System :: POSIX :: Linux
Classifier: Programming Language :: Python
Classifier: Programming Language :: Python :: 2
Classifier: Programming Language :: Python :: 2.7
Classifier: Programming Language :: Python :: 3
Classifier: Programming Language :: Python :: 3.5
